DGraphics/DGraphics.py
DGraphics/__init__.py
DGraphics-6.4.1.dist-info/LICENCE
DGraphics-6.4.1.dist-info/METADATA
DGraphics-6.4.1.dist-info/WHEEL
DGraphics-6.4.1.dist-info/top_level.txt
DGraphics-6.4.1.dist-info/RECORD
